tests/test_multi_mem.py
tests/test_factory.py
tests/__init__.py
tests/test_cffi.py
tests/test_transactions.py
tests/test_hooks.py
tests/test_backup.py
tests/test_formatting.py
tests/test_dump.py
tests/test_userfunctions.py
tests/test_dbapi.py
tests/test_csv.py
tests/test_types.py
tests/test_regression.py
tests/test_dataframe.py
tests/test_lite/test_dbapi01.py
tests/test_lite/test_dbapi05.py
tests/test_lite/conftest.py
tests/test_lite/test_dbapi04.py
tests/test_lite/test_dbapi00.py
tests/test_lite/test_pylite00.py
tests/test_lite/__init__.py
tests/test_lite/test_dbapi03.py
tests/test_lite/test_dbapi02.py
monetdbe/monetize.py
monetdbe/version.py
monetdbe/compat.py
monetdbe/pythonize.py
monetdbe/cursors.py
monetdbe/__init__.py
monetdbe/types.py
monetdbe/formatting.py
monetdbe/dump.py
monetdbe/connection.py
monetdbe/_lowlevel.abi3.so
monetdbe/dbapi2.py
monetdbe/exceptions.py
monetdbe/converters.py
monetdbe/row.py
monetdbe/_cffi/internal.py
monetdbe/_cffi/types_.py
monetdbe/_cffi/util.py
monetdbe/_cffi/__init__.py
monetdbe/_cffi/branch.py
monetdbe/_cffi/builder.py
monetdbe/_cffi/errors.py
monetdbe/_cffi/convert/__init__.py
monetdbe/_cffi/convert/bind.py
monetdbe/.dylibs/libpcre.1.dylib
monetdbe/.dylibs/liblz4.1.9.3.dylib
monetdbe/.dylibs/libmapi.13.dylib
monetdbe/.dylibs/libmonetdbe.2.dylib
monetdbe/.dylibs/libmonetdb5.31.dylib
monetdbe/.dylibs/libmonetdbsql.11.dylib
monetdbe/.dylibs/libbat.23.dylib
monetdbe/.dylibs/liblzma.5.dylib
monetdbe/.dylibs/libstream.15.dylib
monetdbe/.dylibs/libcrypto.1.1.dylib
monetdbe-0.11.dist-info/RECORD
monetdbe-0.11.dist-info/LICENSE
monetdbe-0.11.dist-info/WHEEL
monetdbe-0.11.dist-info/top_level.txt
monetdbe-0.11.dist-info/METADATA
