Metadata-Version: 2.1
Name: monetdbe
Version: 0.11
Summary: MonetDBe - the Python embedded MonetDB
Home-page: https://github.com/monetdBSolutions/MonetDBe-Python/
Author: Gijs Molenaar
Author-email: gijs@pythonic.nl
License: UNKNOWN
Platform: UNKNOWN
Classifier: Programming Language :: Python :: 3
Classifier: Programming Language :: Python :: 3 :: Only
Classifier: License :: OSI Approved :: Mozilla Public License 2.0 (MPL 2.0)
Classifier: Topic :: Database
Classifier: Topic :: Database :: Database Engines/Servers
Classifier: Topic :: Database :: Front-Ends
Requires-Python: >=3.7
License-File: LICENSE
Requires-Dist: cffi (>=1.0.0)
Requires-Dist: numpy
Requires-Dist: pandas
Provides-Extra: doc
Requires-Dist: sphinx ; extra == 'doc'
Requires-Dist: sphinx-rtd-theme ; extra == 'doc'
Provides-Extra: test
Requires-Dist: pytest ; extra == 'test'
Requires-Dist: mypy ; extra == 'test'
Requires-Dist: pycodestyle ; extra == 'test'
Requires-Dist: data-science-types ; extra == 'test'
Requires-Dist: types-setuptools ; extra == 'test'
Requires-Dist: types-pkg-resources ; extra == 'test'
Requires-Dist: types-Jinja2 ; extra == 'test'
Requires-Dist: typing-extensions ; extra == 'test'
